{
  "info": {
    "name": "Go REST API Lab",
    "description": "Complete REST API testing with Bearer token authentication",
    "schema": "https://schema.getpostman.com/json/collection/v2.1.0/collection.json"
  },
  "variable": [
    {
      "key": "base_url",
      "value": "http://localhost:8080",
      "type": "string"
    },
    {
      "key": "token",
      "value": "secret_token_12345",
      "type": "string"
    }
  ],
  "auth": {
    "type": "bearer",
    "bearer": [
      {
        "key": "token",
        "value": "{{token}}",
        "type": "string"
      }
    ]
  },
  "item": [
    {
      "name": "Health Check",
      "request": {
        "auth": {
          "type": "noauth"
        },
        "method": "GET",
        "header": [],
        "url": {
          "raw": "{{base_url}}/health",
          "host": ["{{base_url}}"],
          "path": ["health"]
        }
      }
    },
    {
      "name": "Users",
      "item": [
        {
          "name": "Get User",
          "request": {
            "method": "GET",
            "header": [],
            "url": {
              "raw": "{{base_url}}/users/1",
              "host": ["{{base_url}}"],
              "path": ["users", "1"]
            }
          }
        },
        {
          "name": "Create User",
          "request": {
            "method": "POST",
            "header": [
              {
                "key": "Content-Type",
                "value": "application/json"
              }
            ],
            "body": {
              "mode": "raw",
              "raw": "{\n  \"name\": \"Jane Smith\",\n  \"email\": \"jane.smith@example.com\",\n  \"username\": \"janesmith\"\n}"
            },
            "url": {
              "raw": "{{base_url}}/users",
              "host": ["{{base_url}}"],
              "path": ["users"]
            }
          }
        },
        {
          "name": "Update User (PUT)",
          "request": {
            "method": "PUT",
            "header": [
              {
                "key": "Content-Type",
                "value": "application/json"
              }
            ],
            "body": {
              "mode": "raw",
              "raw": "{\n  \"name\": \"John Updated\",\n  \"email\": \"john.updated@example.com\",\n  \"username\": \"johnupdated\"\n}"
            },
            "url": {
              "raw": "{{base_url}}/users/1",
              "host": ["{{base_url}}"],
              "path": ["users", "1"]
            }
          }
        },
        {
          "name": "Update User (PATCH)",
          "request": {
            "method": "PATCH",
            "header": [
              {
                "key": "Content-Type",
                "value": "application/json"
              }
            ],
            "body": {
              "mode": "raw",
              "raw": "{\n  \"name\": \"John Patched\"\n}"
            },
            "url": {
              "raw": "{{base_url}}/users/1",
              "host": ["{{base_url}}"],
              "path": ["users", "1"]
            }
          }
        },
        {
          "name": "Delete User",
          "request": {
            "method": "DELETE",
            "header": [],
            "url": {
              "raw": "{{base_url}}/users/1",
              "host": ["{{base_url}}"],
              "path": ["users", "1"]
            }
          }
        }
      ]
    },
    {
      "name": "Posts",
      "item": [
        {
          "name": "Get Post",
          "request": {
            "method": "GET",
            "header": [],
            "url": {
              "raw": "{{base_url}}/posts/1",
              "host": ["{{base_url}}"],
              "path": ["posts", "1"]
            }
          }
        },
        {
          "name": "Create Post",
          "request": {
            "method": "POST",
            "header": [
              {
                "key": "Content-Type",
                "value": "application/json"
              }
            ],
            "body": {
              "mode": "raw",
              "raw": "{\n  \"userId\": 1,\n  \"title\": \"My New Post\",\n  \"body\": \"This is the content of my new post\"\n}"
            },
            "url": {
              "raw": "{{base_url}}/posts",
              "host": ["{{base_url}}"],
              "path": ["posts"]
            }
          }
        },
        {
          "name": "Update Post (PUT)",
          "request": {
            "method": "PUT",
            "header": [
              {
                "key": "Content-Type",
                "value": "application/json"
              }
            ],
            "body": {
              "mode": "raw",
              "raw": "{\n  \"userId\": 1,\n  \"title\": \"Updated Post Title\",\n  \"body\": \"This post has been updated\"\n}"
            },
            "url": {
              "raw": "{{base_url}}/posts/1",
              "host": ["{{base_url}}"],
              "path": ["posts", "1"]
            }
          }
        },
        {
          "name": "Delete Post",
          "request": {
            "method": "DELETE",
            "header": [],
            "url": {
              "raw": "{{base_url}}/posts/1",
              "host": ["{{base_url}}"],
              "path": ["posts", "1"]
            }
          }
        }
      ]
    },
    {
      "name": "Auth Tests",
      "item": [
        {
          "name": "No Token (Should Fail)",
          "request": {
            "auth": {
              "type": "noauth"
            },
            "method": "GET",
            "header": [],
            "url": {
              "raw": "{{base_url}}/users/1",
              "host": ["{{base_url}}"],
              "path": ["users", "1"]
            }
          }
        },
        {
          "name": "Wrong Token (Should Fail)",
          "request": {
            "auth": {
              "type": "bearer",
              "bearer": [
                {
                  "key": "token",
                  "value": "wrong_token",
                  "type": "string"
                }
              ]
            },
            "method": "GET",
            "header": [],
            "url": {
              "raw": "{{base_url}}/users/1",
              "host": ["{{base_url}}"],
              "path": ["users", "1"]
            }
          }
        }
      ]
    }
  ]
}
